stream2hop/Utils.py
stream2hop/__init__.py
stream2hop/__main__.py
stream2hop/_version.py
stream2hop/constant.py
stream2hop/gcn2hop.py
stream2hop/tns2hop.py
stream2hop-0.0.3.1.dist-info/LICENSE
stream2hop-0.0.3.1.dist-info/METADATA
stream2hop-0.0.3.1.dist-info/WHEEL
stream2hop-0.0.3.1.dist-info/entry_points.txt
stream2hop-0.0.3.1.dist-info/top_level.txt
stream2hop-0.0.3.1.dist-info/RECORD
